SigProfilerSimulator/SigProfilerSimulator.py
SigProfilerSimulator/__init__.py
SigProfilerSimulator/mutational_simulator.py
SigProfilerSimulator/version.py
sigprofilersimulator-1.2.2.dist-info/licenses/LICENSE
sigprofilersimulator-1.2.2.dist-info/METADATA
sigprofilersimulator-1.2.2.dist-info/WHEEL
sigprofilersimulator-1.2.2.dist-info/top_level.txt
sigprofilersimulator-1.2.2.dist-info/RECORD
