Metadata-Version: 2.4
Name: SigProfilerSimulator
Version: 1.2.2
Summary: SigProfiler simulator tool
Home-page: 
Author: Erik Bergstrom
Author-email: ebergstr@eng.ucsd.edu
License: UCSD
Requires-Python: >=3.9
License-File: LICENSE
Requires-Dist: SigProfilerMatrixGenerator>=1.3.2
Requires-Dist: sigProfilerPlotting>=1.4.0
Requires-Dist: fastrand>=1.2
Dynamic: author
Dynamic: author-email
Dynamic: description
Dynamic: description-content-type
Dynamic: license
Dynamic: license-file
Dynamic: requires-dist
Dynamic: requires-python
Dynamic: summary
